neurokernel/__init__.py
neurokernel/LPU/ControlInterface.py
neurokernel/LPU/LPU.py
neurokernel/LPU/MemoryManager.py
neurokernel/LPU/Transform.py
neurokernel/LPU/__init__.py
neurokernel/LPU/InputProcessors/ArrayInputProcessor.py
neurokernel/LPU/InputProcessors/BaseInputProcessor.py
neurokernel/LPU/InputProcessors/BernoulliInputProcessor.py
neurokernel/LPU/InputProcessors/FileInputProcessor.py
neurokernel/LPU/InputProcessors/PresynapticInputProcessor.py
neurokernel/LPU/InputProcessors/RampInputProcessor.py
neurokernel/LPU/InputProcessors/StepInputProcessor.py
neurokernel/LPU/InputProcessors/__init__.py
neurokernel/LPU/NDComponents/NDComponent.py
neurokernel/LPU/NDComponents/__init__.py
neurokernel/LPU/NDComponents/testing.py
neurokernel/LPU/NDComponents/AxonHillockModels/BaseAxonHillockModel.py
neurokernel/LPU/NDComponents/AxonHillockModels/ConnorStevens.py
neurokernel/LPU/NDComponents/AxonHillockModels/HodgkinHuxley.py
neurokernel/LPU/NDComponents/AxonHillockModels/HodgkinHuxley2.py
neurokernel/LPU/NDComponents/AxonHillockModels/LeakyIAF.py
neurokernel/LPU/NDComponents/AxonHillockModels/LeakyIAFwithRefractoryPeriod.py
neurokernel/LPU/NDComponents/AxonHillockModels/__init__.py
neurokernel/LPU/NDComponents/DendriteModels/Aggregator.py
neurokernel/LPU/NDComponents/DendriteModels/BaseDendriteModel.py
neurokernel/LPU/NDComponents/DendriteModels/__init__.py
neurokernel/LPU/NDComponents/MembraneModels/BaseMembraneModel.py
neurokernel/LPU/NDComponents/MembraneModels/MorrisLecar.py
neurokernel/LPU/NDComponents/MembraneModels/__init__.py
neurokernel/LPU/NDComponents/SynapseModels/AlphaSynapse.py
neurokernel/LPU/NDComponents/SynapseModels/BaseSynapseModel.py
neurokernel/LPU/NDComponents/SynapseModels/PowerGpotGpot.py
neurokernel/LPU/NDComponents/SynapseModels/SigmoidSynapse.py
neurokernel/LPU/NDComponents/SynapseModels/SynapseAMPA.py
neurokernel/LPU/NDComponents/SynapseModels/SynapseGABA.py
neurokernel/LPU/NDComponents/SynapseModels/SynapseNMDA.py
neurodriver-0.3.2.dist-info/AUTHORS.rst
neurodriver-0.3.2.dist-info/LICENSE.rst
neurodriver-0.3.2.dist-info/METADATA
neurodriver-0.3.2.dist-info/WHEEL
neurodriver-0.3.2.dist-info/top_level.txt
neurodriver-0.3.2.dist-info/RECORD
