Metadata-Version: 2.1
Name: neurodriver
Version: 0.3.2
Summary: LPU class with support for various neuron and synapse models
Home-page: https://github.com/neurokernel/neurodriver/
Author: Neurokernel Development Team
Author-email: neurokernel-dev@columbia.edu
Maintainer: Neurokernel Development Team
Maintainer-email: neurokernel-dev@columbia.edu
License: BSD
Platform: UNKNOWN
Classifier: Development Status :: 3 - Alpha
Classifier: Intended Audience :: Developers
Classifier: Intended Audience :: Science/Research
Classifier: License :: OSI Approved :: BSD License
Classifier: Operating System :: OS Independent
Classifier: Programming Language :: Python
Classifier: Topic :: Scientific/Engineering
Classifier: Topic :: Software Development
Requires-Dist: neurokernel (>=0.3.1)
